LICENSE
MANIFEST.in
README.md
setup.py
gears_jsx/__init__.py
gears_jsx/compiler.js
gears_jsx/compiler.py
gears_jsx.egg-info/PKG-INFO
gears_jsx.egg-info/SOURCES.txt
gears_jsx.egg-info/dependency_links.txt
gears_jsx.egg-info/top_level.txt
gears_jsx/node_modules/.DS_Store
gears_jsx/node_modules/.bin/jsx
gears_jsx/node_modules/react-tools/.DS_Store
gears_jsx/node_modules/react-tools/README.md
gears_jsx/node_modules/react-tools/main.js
gears_jsx/node_modules/react-tools/package.json
gears_jsx/node_modules/react-tools/bin/jsx
gears_jsx/node_modules/react-tools/node_modules/.DS_Store
gears_jsx/node_modules/react-tools/node_modules/.bin/commonize
gears_jsx/node_modules/react-tools/node_modules/.bin/esparse
gears_jsx/node_modules/react-tools/node_modules/.bin/esvalidate
gears_jsx/node_modules/react-tools/node_modules/commoner/.npmignore
gears_jsx/node_modules/react-tools/node_modules/commoner/.travis.yml
gears_jsx/node_modules/react-tools/node_modules/commoner/LICENSE
gears_jsx/node_modules/react-tools/node_modules/commoner/README.md
gears_jsx/node_modules/react-tools/node_modules/commoner/main.js
gears_jsx/node_modules/react-tools/node_modules/commoner/package.json
gears_jsx/node_modules/react-tools/node_modules/commoner/bin/commonize
gears_jsx/node_modules/react-tools/node_modules/commoner/lib/cache.js
gears_jsx/node_modules/react-tools/node_modules/commoner/lib/commoner.js
gears_jsx/node_modules/react-tools/node_modules/commoner/lib/context.js
gears_jsx/node_modules/react-tools/node_modules/commoner/lib/grep.js
gears_jsx/node_modules/react-tools/node_modules/commoner/lib/output.js
gears_jsx/node_modules/react-tools/node_modules/commoner/lib/reader.js
gears_jsx/node_modules/react-tools/node_modules/commoner/lib/relative.js
gears_jsx/node_modules/react-tools/node_modules/commoner/lib/util.js
gears_jsx/node_modules/react-tools/node_modules/commoner/lib/watcher.js
gears_jsx/node_modules/react-tools/node_modules/commoner/node_modules/.bin/whiskey
gears_jsx/node_modules/react-tools/node_modules/commoner/node_modules/commander/Readme.md
