Metadata-Version: 1.1
Name: gears-jsx
Version: 0.1
Summary: JSX compiler for Gears
Home-page: https://github.com/ChillyBwoy/gears-jsx
Author: Eugene Cheltsov
Author-email: chill.icp@gmail.com
License: ISC
Keywords: gears django-gears react jsx gears-jsx
Platform: UNKNOWN
Classifier: Development Status :: 3 - Alpha
Classifier: Intended Audience :: Developers
Classifier: License :: OSI Approved :: ISC License (ISCL)
Classifier: Operating System :: OS Independent
Classifier: Programming Language :: Python
Classifier: Programming Language :: Python :: 2.7
